pcf_config/__init__.py
pcf_config/config.py
pcf_config-1.1.9.dist-info/METADATA
pcf_config-1.1.9.dist-info/WHEEL
pcf_config-1.1.9.dist-info/top_level.txt
pcf_config-1.1.9.dist-info/RECORD
