Metadata-Version: 2.1
Name: pcf-config
Version: 1.1.9
Summary: A simple YAML configuration management library
Author-email: pengcunfu <3173484026@qq.com>
Maintainer-email: pengcunfu <3173484026@qq.com>
Project-URL: Homepage, https://github.com/pengcunfu/pcf-config
Project-URL: Repository, https://github.com/pengcunfu/pcf-config
Project-URL: Documentation, https://github.com/pengcunfu/pcf-config#readme
Project-URL: Bug Tracker, https://github.com/pengcunfu/pcf-config/issues
Keywords: config,yaml,configuration,settings
Classifier: Development Status :: 5 - Production/Stable
Classifier: Intended Audience :: Developers
Classifier: Operating System :: OS Independent
Classifier: Programming Language :: Python :: 3
Classifier: Programming Language :: Python :: 3.9
Classifier: Programming Language :: Python :: 3.10
Classifier: Programming Language :: Python :: 3.11
Classifier: Programming Language :: Python :: 3.12
Classifier: Topic :: Software Development :: Libraries :: Python Modules
Classifier: Topic :: System :: Systems Administration
Classifier: Topic :: Utilities
Requires-Python: >=3.9
Requires-Dist: PyYAML>=5.1.0
Provides-Extra: dev
Requires-Dist: pytest>=6.0.0; extra == "dev"
Requires-Dist: pytest-cov>=2.10.0; extra == "dev"
Requires-Dist: black>=21.0.0; extra == "dev"
Requires-Dist: flake8>=3.8.0; extra == "dev"
Requires-Dist: mypy>=0.800; extra == "dev"
